{
    "title": "Beer Can Chicken",
    "meta": "",
    "ingredients": [
        "1 4 lb whole chicken",
        "Applewood chips",
        "1 12oz can of pale ale beer",
        "1 cup apple cider",
        "&frac12; cup apple cider vinegar",
        "4 TBSP butter (melted)",
        "1 cup olive oil",
        "1 cup cajun seasoning",
        "1 tsp garlic powder",
        "1 tsp onion powder"
    ],
    "directions": [
        { "text": "In a small bowl whisk together the butter, vinegar, &frac14; cup cajun seasoning, garlic powder, and onion powder." },
        { "text": "Use a meat injecting syringe to inject bowl contents into various spots of the chicken." },
        { "text": "Rub the chicken all over with a &frac12; cup olive oil and a generous layer of cajon seasoning." },
        { "text": "Discard half of the beer and put the can in the chicken's cavity and set it upright." },
        { "text": "Heat smoker to 250°." },
        { "text": "Make a mop by the pouring cider and &frac12; cup olive oil into a spray bottle." },
        { "text": "Smoke chicken for about 3 hours until it reaches 165°" },
        { "text": "Add Applewood chips every 30 mins up to an hour." },
        { "text": "Spray chicken with the mop every 30 minutes." }
    ]
}
