{
    "title": "Raspberry Nectarine Pie Filling",
    "meta": "",
    "ingredients": [
        "4 Nectarines",
        "10 oz raspberries",
        "1 lemon",
        "1 cup sugar",
        "4 tsp cornstarch",
        "A pinch of salt"
    ],
    "directions": [
        { "text": "Cut up nectarines into &frac12; inch size pieces." },
        { "text": "Gently toss nectarines, raspberries, &frac12; cup sugar in a bowl and let sit for 20 mins." },
        { "text": "Keep 2 TBSP fruit juice from bowl then drain fruit in a colander." },
        { "text": "Toss fruit with &frac12 tsp lemon zest, 1&frac12; tsp lemon juice, cornstarch, a pinch of salt and 1 TBSP more sugar." }
    ]
}
